tendulkar_s3_aws/__init__.py
tendulkar_s3_aws/sdk/wallpaper_s3_client.py
tendulkar_s3_aws-0.0.1.dist-info/METADATA
tendulkar_s3_aws-0.0.1.dist-info/WHEEL
tendulkar_s3_aws-0.0.1.dist-info/top_level.txt
tendulkar_s3_aws-0.0.1.dist-info/RECORD
