Metadata-Version: 2.1
Name: tendulkar-s3-aws
Version: 0.0.1
Summary: Python library for dashboard
Home-page: https://github.com/tendulkar/tendulkar-utils
Author: Shubham Tendulkar
Author-email: shubhamtendulkar@gmail.com
License: UNKNOWN
Platform: UNKNOWN
Requires-Dist: colorama
Requires-Dist: colorlog
Requires-Dist: requests
